Exercise 1/alu.v
module alu (
	input  [31:0] A, input [31:0] B, input [1:0] ALUControl, // Declaration ofinputs and ALUControl signal, A & B support 32 bits
	output reg [31:0] Result, output [3:0] ALUFlags  // Declaration of module outputs 
);
	wire [31:0] mux2_1; // Wire to hold the output of the mux2:1 
	wire [32:0] Sum; // Wire that will hold the sum of A and B if it is required
	wire Overflow, Carry,Negative, Zero; // Wires that hold each ALU Flag
    
	assign mux2_1 = (ALUControl[0]==0)? B: ~B; // MUX 2:1 simplification using the conditional operator
	assign Sum = A+mux2_1+ALUControl[0]; // Definition of the ADDER module

	// MUX 4:1 simplification using the CASE keyword & syntax
	always @(*) begin
		casex (ALUControl)
			2'b0?: Result = Sum; // ALUControl signal 00/01 means ADD and SUB, so either way A and B will be added
			2'b10: Result = A & B; // ALUControl signal 10 means AND
			2'b11: Result = A | B; // ALUControl signal 01 means OR
		endcase
	end

  assign Overflow = ~(ALUControl[0]^A[31]^B[31]) & (Sum[31]^A[31]) & ~ALUControl[1]; // Overflow flag wire
	assign Zero = 32'b0 == Result; // If every bit is 0, then the zero result flag will activate
	assign Negative = Result[31]; // If the first bit from the left is 1,  the result will be negative
	assign Carry = ~ALUControl[1] & Sum[32]; // Carry will be 1 if the ALUControl signal is addition or subtraction and if the 1st bit from the left bit is 1

	assign ALUFlags = {Negative, Zero, Carry, Overflow}; // We group each bit-flag to the ALUFlags output    

	initial
	$display("%d %d %d %d %d", A, B, ALUControl, Result, ALUFlags);

endmodule

Exercise 1/arm_single.v
`include "alu.v"
module testbench;
	reg clk;
	reg reset;
	wire [31:0] WriteData;
	wire [31:0] DataAdr;
	wire MemWrite;
	top dut(
		.clk(clk),
		.reset(reset),
		.WriteData(WriteData),
		.DataAdr(DataAdr),
		.MemWrite(MemWrite)
	);
	initial begin
		reset <= 1;
		#(22);
		reset <= 0;
	end
	always begin
		clk <= 1;
		#(5);
		clk <= 0;
		#(5);
	end
	always @(negedge clk) begin
		if (MemWrite) begin
			if ((DataAdr === 100) & (WriteData === 7)) begin
				$display("Simulation succeeded");
				$finish;
			end
			else if (DataAdr !== 96) begin
				$display("Simulation failed");
				$finish;
			end
		end
	end

	initial begin
		$dumpfile("arm.vcd");
		$dumpvars;
	end
endmodule

module top (
	input wire clk,
	input wire reset,
	output wire [31:0] WriteData,
	output wire [31:0] DataAdr,
	output wire MemWrite
);
	wire [31:0] PC;
	wire [31:0] Instr;
	wire [31:0] ReadData;
	arm arm(
		.clk(clk),
		.reset(reset),
		.PC(PC),
		.Instr(Instr),
		.MemWrite(MemWrite),
		.ALUResult(DataAdr),
		.WriteData(WriteData),
		.ReadData(ReadData)
	);
	imem imem(
		.a(PC),
		.rd(Instr)
	);
	
	dmem dmem(
		.clk(clk),
		.we(MemWrite),
		.a(DataAdr),
		.wd(WriteData),
		.rd(ReadData)
	);
endmodule
module dmem (
	input wire clk,
	input wire we,
	input wire [31:0] a,
	input wire [31:0] wd,
	output wire [31:0] rd
);
	
	reg [31:0] RAM [63:0];

/* 	integer i=0;
	initial begin
		for(i = 0; i<64; i=i+1)
			RAM[i] = 0;
	end */

	assign rd = RAM[a[31:2]];

	always @(posedge clk) begin
		if (we) begin
			RAM[a[31:2]] <= wd;
		end
	end
endmodule
module imem (
	input wire [31:0] a,
	output wire [31:0] rd
);

	reg [31:0] RAM [22:0];
	initial begin 
		$readmemh("memfile.dat", RAM);
	end

	assign rd = RAM[a[31:2]];
endmodule
module arm (
	input wire clk,
	input wire reset,
	output wire [31:0] PC,
	input wire [31:0] Instr,
	output wire MemWrite,
	output wire [31:0] ALUResult,
	output wire [31:0] WriteData,
	input wire [31:0] ReadData
);
	wire [3:0] ALUFlags;
	wire RegWrite;
	wire ALUSrc;
	wire MemtoReg;
	wire PCSrc;
	wire [1:0] RegSrc;
	wire [1:0] ImmSrc;
	wire [1:0] ALUControl;
	controller c(
		.clk(clk),
		.reset(reset),
		.Instr(Instr[31:12]),
		.ALUFlags(ALUFlags),
		.RegSrc(RegSrc),
		.RegWrite(RegWrite),
		.ImmSrc(ImmSrc),
		.ALUSrc(ALUSrc),
		.ALUControl(ALUControl),
		.MemWrite(MemWrite),
		.MemtoReg(MemtoReg),
		.PCSrc(PCSrc)
	);
	datapath dp(
		.clk(clk),
		.reset(reset),
		.RegSrc(RegSrc),
		.RegWrite(RegWrite),
		.ImmSrc(ImmSrc),
		.ALUSrc(ALUSrc),
		.ALUControl(ALUControl),
		.MemtoReg(MemtoReg),
		.PCSrc(PCSrc),
		.ALUFlags(ALUFlags),
		.PC(PC),
		.Instr(Instr),
		.ALUResult(ALUResult),
		.WriteData(WriteData),
		.ReadData(ReadData)
	);
endmodule
module controller (
	input wire clk,
	input wire reset,
	input wire [31:12] Instr,
	input wire [3:0] ALUFlags,
	output wire [1:0] RegSrc,
	output wire RegWrite,
	output wire [1:0] ImmSrc,
	output wire ALUSrc,
	output wire [1:0] ALUControl,
	output wire MemWrite,
	output wire MemtoReg,
	output wire PCSrc
);
	wire [1:0] FlagW;
	wire PCS;
	wire RegW;
	wire MemW;
	decode dec(
		.Op(Instr[27:26]),
		.Funct(Instr[25:20]),
		.Rd(Instr[15:12]),
		.FlagW(FlagW),
		.PCS(PCS),
		.RegW(RegW),
		.MemW(MemW),
		.MemtoReg(MemtoReg),
		.ALUSrc(ALUSrc),
		.ImmSrc(ImmSrc),
		.RegSrc(RegSrc),
		.ALUControl(ALUControl)
	);
	condlogic cl(
		.clk(clk),
		.reset(reset),
		.Cond(Instr[31:28]),
		.ALUFlags(ALUFlags),
		.FlagW(FlagW),
		.PCS(PCS),
		.RegW(RegW),
		.MemW(MemW),
		.PCSrc(PCSrc),
		.RegWrite(RegWrite),
		.MemWrite(MemWrite)
	);
endmodule
module decode (
	input wire [1:0] Op,
	input wire [5:0] Funct,
	input wire [3:0] Rd,
	output reg [1:0] FlagW,
	output wire PCS,
	output wire RegW,
	output wire MemW,
	output wire MemtoReg,
	output wire ALUSrc,
	output wire [1:0] ImmSrc,
	output wire [1:0] RegSrc,
	output reg [1:0] ALUControl
);
	reg [9:0] controls;
	wire Branch;
	wire ALUOp;
	always @(*) begin
		casex (Op)
			2'b00:
				if (Funct[5])
					controls = 10'b0000101001;
				else
					controls = 10'b0000001001;
			2'b01:
				if (Funct[0])
					controls = 10'b0001111000;
				else
					controls = 10'b1001110100;
			2'b10: controls = 10'b0110100010;
			default: controls = 10'bxxxxxxxxxx;
		endcase
	end
	assign {RegSrc, ImmSrc, ALUSrc, MemtoReg, RegW, MemW, Branch, ALUOp} = controls;
	always @(*) begin
		if (ALUOp) begin
			case (Funct[4:1])
				4'b0100: ALUControl = 2'b00;
				4'b0010: ALUControl = 2'b01;
				4'b0000: ALUControl = 2'b10;
				4'b1100: ALUControl = 2'b11;
				default: ALUControl = 2'bxx;
			endcase
			FlagW[1] = Funct[0];
			FlagW[0] = Funct[0] & ((ALUControl == 2'b00) | (ALUControl == 2'b01));
		end
		else begin
			ALUControl = 2'b00;
			FlagW = 2'b00;
		end
	end
	assign PCS = ((Rd == 4'b1111) & RegW) | Branch;
endmodule
module condlogic (
	input wire clk,
	input wire reset,
	input wire [3:0] Cond,
	input wire [3:0] ALUFlags,
	input wire [1:0] FlagW,
	input wire PCS,
	input wire RegW,
	input wire MemW,
	output wire PCSrc,
	output wire RegWrite,
	output wire MemWrite
);
	wire [1:0] FlagWrite;
	wire [3:0] Flags;
	wire CondEx;
	flopenr #(2) flagreg1(
		.clk(clk),
		.reset(reset),
		.en(FlagWrite[1]),
		.d(ALUFlags[3:2]),
		.q(Flags[3:2])
	);
	flopenr #(2) flagreg0(
		.clk(clk),
		.reset(reset),
		.en(FlagWrite[0]),
		.d(ALUFlags[1:0]),
		.q(Flags[1:0])
	);
	condcheck cc(
		.Cond(Cond),
		.Flags(Flags),
		.CondEx(CondEx)
	);
	assign FlagWrite = FlagW & {2 {CondEx}};
	assign RegWrite = RegW & CondEx;
	assign MemWrite = MemW & CondEx;
	assign PCSrc = PCS & CondEx;
endmodule
module condcheck (
	input wire [3:0] Cond,
	input wire [3:0] Flags,
	output reg CondEx
);
	wire neg;
	wire zero;
	wire carry;
	wire overflow;
	wire ge;
	assign {neg, zero, carry, overflow} = Flags;
	assign ge = neg == overflow;
	always @(*)
		case (Cond)
			4'b0000: CondEx = zero;
			4'b0001: CondEx = ~zero;
			4'b0010: CondEx = carry;
			4'b0011: CondEx = ~carry;
			4'b0100: CondEx = neg;
			4'b0101: CondEx = ~neg;
			4'b0110: CondEx = overflow;
			4'b0111: CondEx = ~overflow;
			4'b1000: CondEx = carry & ~zero;
			4'b1001: CondEx = ~(carry & ~zero);
			4'b1010: CondEx = ge;
			4'b1011: CondEx = ~ge;
			4'b1100: CondEx = ~zero & ge;
			4'b1101: CondEx = ~(~zero & ge);
			4'b1110: CondEx = 1'b1;
			default: CondEx = 1'bx;
		endcase
endmodule
module datapath (
	input wire clk,
	input wire reset,
	input wire [1:0] RegSrc,
	input wire RegWrite,
	input wire [1:0] ImmSrc,
	input wire ALUSrc,
	input wire [1:0] ALUControl,
	input wire MemtoReg,
	input wire PCSrc,
	output wire [3:0] ALUFlags,
	output wire [31:0] PC,
	input wire [31:0] Instr,
	output wire [31:0] ALUResult,
	output wire [31:0] WriteData,
	input wire [31:0] ReadData
);
	wire [31:0] PCNext;
	wire [31:0] PCPlus4;
	wire [31:0] PCPlus8;
	wire [31:0] ExtImm;
	wire [31:0] SrcA;
	wire [31:0] SrcB;
	wire [31:0] Result;
	wire [3:0] RA1;
	wire [3:0] RA2;
	mux2 #(32) pcmux(
		.d0(PCPlus4),
		.d1(Result),
		.s(PCSrc),
		.y(PCNext)
	);
	flopr #(32) pcreg(
		.clk(clk),
		.reset(reset),
		.d(PCNext),
		.q(PC)
	);
	adder #(32) pcadd1(
		.a(PC),
		.b(32'b100),
		.y(PCPlus4)
	);
	adder #(32) pcadd2(
		.a(PCPlus4),
		.b(32'b100),
		.y(PCPlus8)
	);
	mux2 #(4) ra1mux(
		.d0(Instr[19:16]),
		.d1(4'b1111),
		.s(RegSrc[0]),
		.y(RA1)
	);
	mux2 #(4) ra2mux(
		.d0(Instr[3:0]),
		.d1(Instr[15:12]),
		.s(RegSrc[1]),
		.y(RA2)
	);
	regfile rf(
		.clk(clk),
		.we3(RegWrite),
		.ra1(RA1),
		.ra2(RA2),
		.wa3(Instr[15:12]),
		.wd3(Result),
		.r15(PCPlus8),
		.rd1(SrcA),
		.rd2(WriteData)
	);
	mux2 #(32) resmux(
		.d0(ALUResult),
		.d1(ReadData),
		.s(MemtoReg),
		.y(Result)
	);
	extend ext(
		.Instr(Instr[23:0]),
		.ImmSrc(ImmSrc),
		.ExtImm(ExtImm)
	);
	mux2 #(32) srcbmux(
		.d0(WriteData),
		.d1(ExtImm),
		.s(ALUSrc),
		.y(SrcB)
	);

	alu alu(
		.A(SrcA),
		.B(SrcB),
		.ALUControl(ALUControl),
		.Result(ALUResult),
		.ALUFlags(ALUFlags)
	);
	
endmodule
module regfile (
	input wire clk,
	input wire we3,
	input wire [3:0] ra1,
	input wire [3:0] ra2,
	input wire [3:0] wa3,
	input wire [31:0] wd3,
	input wire [31:0] r15,
	output wire [31:0] rd1,
	output wire [31:0] rd2
);


	reg [31:0] rf [14:0];
	always @(posedge clk) begin
		if (we3)
			rf[wa3] <= wd3;
	end
	assign rd1 = (ra1 == 4'b1111 ? r15 : rf[ra1]);
	assign rd2 = (ra2 == 4'b1111 ? r15 : rf[ra2]);
endmodule
module extend (
	input wire [23:0] Instr,
	input wire [1:0] ImmSrc,
	output reg [31:0] ExtImm
);
	always @(*) begin
		case (ImmSrc)
			2'b00: ExtImm = {24'b000000000000000000000000, Instr[7:0]};
			2'b01: ExtImm = {20'b00000000000000000000, Instr[11:0]};
			2'b10: ExtImm = {{6 {Instr[23]}}, Instr[23:0], 2'b00};
			default: ExtImm = 32'bxxxxxxxxxxxxxxxxxxxxxxxxxxxxxxxx;
		endcase
	end
endmodule
module adder (
	a,
	b,
	y
);
	parameter WIDTH = 8;
	input wire [WIDTH - 1:0] a;
	input wire [WIDTH - 1:0] b;
	output wire [WIDTH - 1:0] y;
	assign y = a + b;
endmodule
module flopenr (
	clk,
	reset,
	en,
	d,
	q
);
	parameter WIDTH = 8;
	input wire clk;
	input wire reset;
	input wire en;
	input wire [WIDTH - 1:0] d;
	output reg [WIDTH - 1:0] q;
	always @(posedge clk or posedge reset) begin
		if (reset)
			q <= 0;
		else if (en)
			q <= d;
	end
endmodule
module flopr (
	clk,
	reset,
	d,
	q
);
	parameter WIDTH = 8;
	input wire clk;
	input wire reset;
	input wire [WIDTH - 1:0] d;
	output reg [WIDTH - 1:0] q;
	always @(posedge clk or posedge reset) begin
		if (reset)
			q <= 0;
		else
			q <= d;
	end
endmodule
module mux2 (
	d0,
	d1,
	s,
	y
);
	parameter WIDTH = 8;
	input wire [WIDTH - 1:0] d0;
	input wire [WIDTH - 1:0] d1;
	input wire s;
	output wire [WIDTH - 1:0] y;
	assign y = (s ? d1 : d0);
endmodule

Exercise 1/arm.vcd
$date
	Tue Nov 30 18:03:46 2021
$end
$version
	Icarus Verilog
$end
$timescale
	1s
$end
$scope module testbench $end
$var wire 32 ! WriteData [31:0] $end
$var wire 1 " MemWrite $end
$var wire 32 # DataAdr [31:0] $end
$var reg 1 $ clk $end
$var reg 1 % reset $end
$scope module dut $end
$var wire 1 $ clk $end
$var wire 1 % reset $end
$var wire 32 & WriteData [31:0] $end
$var wire 32 ' ReadData [31:0] $end
$var wire 32 ( PC [31:0] $end
$var wire 1 " MemWrite $end
$var wire 32 ) Instr [31:0] $end
$var wire 32 * DataAdr [31:0] $end
$scope module arm $end
$var wire 1 $ clk $end
$var wire 1 % reset $end
$var wire 32 + WriteData [31:0] $end
$var wire 1 , RegWrite $end
$var wire 2 - RegSrc [1:0] $end
$var wire 32 . ReadData [31:0] $end
$var wire 1 / PCSrc $end
$var wire 32 0 PC [31:0] $end
$var wire 1 1 MemtoReg $end
$var wire 1 " MemWrite $end
$var wire 32 2 Instr [31:0] $end
$var wire 2 3 ImmSrc [1:0] $end
$var wire 1 4 ALUSrc $end
$var wire 32 5 ALUResult [31:0] $end
$var wire 4 6 ALUFlags [3:0] $end
$var wire 2 7 ALUControl [1:0] $end
$scope module c $end
$var wire 20 8 Instr [31:12] $end
$var wire 1 $ clk $end
$var wire 1 % reset $end
$var wire 1 , RegWrite $end
$var wire 1 9 RegW $end
$var wire 2 : RegSrc [1:0] $end
$var wire 1 / PCSrc $end
$var wire 1 ; PCS $end
$var wire 1 1 MemtoReg $end
$var wire 1 " MemWrite $end
$var wire 1 < MemW $end
$var wire 2 = ImmSrc [1:0] $end
$var wire 2 > FlagW [1:0] $end
$var wire 1 4 ALUSrc $end
$var wire 4 ? ALUFlags [3:0] $end
$var wire 2 @ ALUControl [1:0] $end
$scope module cl $end
$var wire 4 A Cond [3:0] $end
$var wire 2 B FlagWrite [1:0] $end
$var wire 1 " MemWrite $end
$var wire 1 / PCSrc $end
$var wire 1 , RegWrite $end
$var wire 1 $ clk $end
$var wire 1 % reset $end
$var wire 1 9 RegW $end
$var wire 1 ; PCS $end
$var wire 1 < MemW $end
$var wire 4 C Flags [3:0] $end
$var wire 2 D FlagW [1:0] $end
$var wire 1 E CondEx $end
$var wire 4 F ALUFlags [3:0] $end
$scope module cc $end
$var wire 4 G Cond [3:0] $end
$var wire 4 H Flags [3:0] $end
$var wire 1 I ge $end
$var wire 1 J zero $end
$var wire 1 K overflow $end
$var wire 1 L neg $end
$var wire 1 M carry $end
$var reg 1 E CondEx $end
$upscope $end
$scope module flagreg0 $end
$var wire 1 $ clk $end
$var wire 2 N d [1:0] $end
$var wire 1 O en $end
$var wire 1 % reset $end
$var reg 2 P q [1:0] $end
$upscope $end
$scope module flagreg1 $end
$var wire 1 $ clk $end
$var wire 2 Q d [1:0] $end
$var wire 1 R en $end
$var wire 1 % reset $end
$var reg 2 S q [1:0] $end
$upscope $end
$upscope $end
$scope module dec $end
$var wire 6 T Funct [5:0] $end
$var wire 2 U Op [1:0] $end
$var wire 1 ; PCS $end
$var wire 4 V Rd [3:0] $end
$var wire 1 9 RegW $end
$var wire 2 W RegSrc [1:0] $end
$var wire 1 1 MemtoReg $end
$var wire 1 < MemW $end
$var wire 2 X ImmSrc [1:0] $end
$var wire 1 Y Branch $end
$var wire 1 4 ALUSrc $end
$var wire 1 Z ALUOp $end
$var reg 2 [ ALUControl [1:0] $end
$var reg 2 \ FlagW [1:0] $end
$var reg 10 ] controls [9:0] $end
$upscope $end
$upscope $end
$scope module dp $end
$var wire 2 ^ ALUControl [1:0] $end
$var wire 1 4 ALUSrc $end
$var wire 2 _ ImmSrc [1:0] $end
$var wire 1 1 MemtoReg $end
$var wire 1 / PCSrc $end
$var wire 2 ` RegSrc [1:0] $end
$var wire 1 , RegWrite $end
$var wire 1 $ clk $end
$var wire 1 % reset $end
$var wire 32 a WriteData [31:0] $end
$var wire 32 b SrcB [31:0] $end
$var wire 32 c SrcA [31:0] $end
$var wire 32 d Result [31:0] $end
$var wire 32 e ReadData [31:0] $end
$var wire 4 f RA2 [3:0] $end
$var wire 4 g RA1 [3:0] $end
$var wire 32 h PCPlus8 [31:0] $end
$var wire 32 i PCPlus4 [31:0] $end
$var wire 32 j PCNext [31:0] $end
$var wire 32 k PC [31:0] $end
$var wire 32 l Instr [31:0] $end
$var wire 32 m ExtImm [31:0] $end
$var wire 32 n ALUResult [31:0] $end
$var wire 4 o ALUFlags [3:0] $end
$scope module alu $end
$var wire 2 p ALUControl [1:0] $end
$var wire 1 q Carry $end
$var wire 1 r Overflow $end
$var wire 32 s mux2_1 [31:0] $end
$var wire 1 t Zero $end
$var wire 33 u Sum [32:0] $end
$var wire 1 v Negative $end
$var wire 32 w B [31:0] $end
$var wire 4 x ALUFlags [3:0] $end
$var wire 32 y A [31:0] $end
$var reg 32 z Result [31:0] $end
$upscope $end
$scope module ext $end
$var wire 2 { ImmSrc [1:0] $end
$var wire 24 | Instr [23:0] $end
$var reg 32 } ExtImm [31:0] $end
$upscope $end
$scope module pcadd1 $end
$var wire 32 ~ b [31:0] $end
$var wire 32 !" y [31:0] $end
$var wire 32 "" a [31:0] $end
$upscope $end
$scope module pcadd2 $end
$var wire 32 #" a [31:0] $end
$var wire 32 $" b [31:0] $end
$var wire 32 %" y [31:0] $end
$upscope $end
$scope module pcmux $end
$var wire 32 &" d0 [31:0] $end
$var wire 1 / s $end
$var wire 32 '" y [31:0] $end
$var wire 32 (" d1 [31:0] $end
$upscope $end
$scope module pcreg $end
$var wire 1 $ clk $end
$var wire 32 )" d [31:0] $end
$var wire 1 % reset $end
$var reg 32 *" q [31:0] $end
$upscope $end
$scope module ra1mux $end
$var wire 4 +" d0 [3:0] $end
$var wire 4 ," d1 [3:0] $end
$var wire 1 -" s $end
$var wire 4 ." y [3:0] $end
$upscope $end
$scope module ra2mux $end
$var wire 4 /" d0 [3:0] $end
$var wire 4 0" d1 [3:0] $end
$var wire 1 1" s $end
$var wire 4 2" y [3:0] $end
$upscope $end
$scope module resmux $end
$var wire 32 3" d0 [31:0] $end
$var wire 1 1 s $end
$var wire 32 4" y [31:0] $end
$var wire 32 5" d1 [31:0] $end
$upscope $end
$scope module rf $end
$var wire 1 $ clk $end
$var wire 32 6" r15 [31:0] $end
$var wire 4 7" ra1 [3:0] $end
$var wire 4 8" ra2 [3:0] $end
$var wire 4 9" wa3 [3:0] $end
$var wire 32 :" wd3 [31:0] $end
$var wire 1 , we3 $end
$var wire 32 ;" rd2 [31:0] $end
$var wire 32 <" rd1 [31:0] $end
$upscope $end
$scope module srcbmux $end
$var wire 32 =" d0 [31:0] $end
$var wire 32 >" d1 [31:0] $end
$var wire 1 4 s $end
$var wire 32 ?" y [31:0] $end
$upscope $end
$upscope $end
$upscope $end
$scope module dmem $end
$var wire 32 @" a [31:0] $end
$var wire 1 $ clk $end
$var wire 32 A" rd [31:0] $end
$var wire 32 B" wd [31:0] $end
$var wire 1 " we $end
$upscope $end
$scope module imem $end
$var wire 32 C" a [31:0] $end
$var wire 32 D" rd [31:0] $end
$upscope $end
$upscope $end
$upscope $end
$enddefinitions $end
#0
$dumpvars
b11100000010011110000000000001111 D"
b0 C"
b1000 B"
bx A"
b0 @"
b1000 ?"
b1111 >"
b1000 ="
b1000 <"
b1000 ;"
b0 :"
b0 9"
b1111 8"
b1111 7"
b1000 6"
bx 5"
b0 4"
b0 3"
b1111 2"
01"
b0 0"
b1111 /"
b1111 ."
0-"
b1111 ,"
b1111 +"
b0 *"
b100 )"
b0 ("
b100 '"
b100 &"
b1000 %"
b100 $"
b100 #"
b0 ""
b100 !"
b100 ~
b1111 }
b10011110000000000001111 |
b0 {
b0 z
b1000 y
b110 x
b1000 w
0v
b100000000000000000000000000000000 u
1t
b11111111111111111111111111110111 s
0r
1q
b1 p
b110 o
b0 n
b1111 m
b11100000010011110000000000001111 l
b0 k
b100 j
b100 i
b1000 h
b1111 g
b1111 f
bx e
b0 d
b1000 c
b1000 b
b1000 a
b0 `
b0 _
b1 ^
b1001 ]
b0 \
b1 [
1Z
0Y
b0 X
b0 W
b0 V
b0 U
b100 T
b0 S
0R
b1 Q
b0 P
0O
b10 N
0M
0L
0K
0J
1I
b0 H
b1110 G
b110 F
1E
b0 D
b0 C
b0 B
b1110 A
b1 @
b110 ?
b0 >
b0 =
0<
0;
b0 :
19
b11100000010011110000 8
b1 7
b110 6
b0 5
04
b0 3
b11100000010011110000000000001111 2
01
b0 0
0/
bx .
b0 -
1,
b1000 +
b0 *
b11100000010011110000000000001111 )
b0 (
bx '
b1000 &
1%
1$
b0 #
0"
b1000 !
$end
#5
0$
#10
1$
#15
0$
#20
1$
#22
0%
#25
0$
#30
b0 N
0q
0v
14
b0 7
b0 @
b0 [
b0 ^
b0 p
b101001 ]
b101 s
b101 m
b101 }
b101 >"
b101 f
b101 2"
b101 8"
b0 g
b0 ."
b0 7"
b101000 T
b10 V
b0 Q
b101 d
b101 ("
b101 4"
b101 :"
b100000000010000000000101 |
b10 9"
b10 0"
b101 /"
b0 +"
b11100010100000000010 8
b0 6
b0 ?
b0 F
b0 o
b0 x
0t
b101 #
b101 *
b101 5
b101 n
b101 z
b101 3"
b101 @"
b101 b
b101 w
b101 ?"
b11100010100000000010000000000101 )
b11100010100000000010000000000101 2
b11100010100000000010000000000101 l
b11100010100000000010000000000101 D"
b101 u
b0 c
b0 y
b0 <"
bx !
bx &
bx +
bx a
bx ;"
bx ="
bx B"
b1000 j
b1000 '"
b1000 )"
b1100 h
b1100 %"
b1100 6"
b1000 i
b1000 !"
b1000 #"
b1000 &"
b100 (
b100 0
b100 k
b100 ""
b100 *"
b100 C"
1$
#35
0$
#40
b1100 d
b1100 ("
b1100 4"
b1100 :"
b1100 #
b1100 *
b1100 5
b1100 n
b1100 z
b1100 3"
b1100 @"
b1100 u
b1100 s
b1100 b
b1100 w
b1100 ?"
b1100 m
b1100 }
b1100 >"
b1100 f
b1100 2"
b1100 8"
b11 V
b100000000011000000001100 |
b11 9"
b11 0"
b1100 /"
b11100010100000000011 8
b11100010100000000011000000001100 )
b11100010100000000011000000001100 2
b11100010100000000011000000001100 l
b11100010100000000011000000001100 D"
b1100 j
b1100 '"
b1100 )"
b10000 h
b10000 %"
b10000 6"
b1100 i
b1100 !"
b1100 #"
b1100 &"
b1000 (
b1000 0
b1000 k
b1000 ""
b1000 *"
b1000 C"
1$
#45
0$
#50
b10 N
b10 6
b10 ?
b10 F
b10 o
b10 x
1q
b11 d
b11 ("
b11 4"
b11 :"
b11111111111111111111111111110110 s
b11 #
b11 *
b11 5
b11 n
b11 z
b11 3"
b11 @"
b1001 b
b1001 w
b1001 ?"
b100000000000000000000000000000011 u
b1100 c
b1100 y
b1100 <"
b1 7
b1 @
b1 [
b1 ^
b1 p
b1001 m
b1001 }
b1001 >"
b1001 f
b1001 2"
b1001 8"
b11 g
b11 ."
b11 7"
b100100 T
b111 V
b10000110111000000001001 |
b111 9"
b111 0"
b1001 /"
b11 +"
b11100010010000110111 8
b11100010010000110111000000001001 )
b11100010010000110111000000001001 2
b11100010010000110111000000001001 l
b11100010010000110111000000001001 D"
b10000 j
b10000 '"
b10000 )"
b10100 h
b10100 %"
b10100 6"
b10000 i
b10000 !"
b10000 #"
b10000 &"
b1100 (
b1100 0
b1100 k
b1100 ""
b1100 *"
b1100 C"
1$
#55
0$
#60
b111 d
b111 ("
b111 4"
b111 :"
b0 N
b111 #
b111 *
b111 5
b111 n
b111 z
b111 3"
b111 @"
b11111111111111111111111111111010 s
b0 6
b0 ?
b0 F
b0 o
b0 x
0q
04
b101 b
b101 w
b101 ?"
b101 !
b101 &
b101 +
b101 a
b101 ;"
b101 ="
b101 B"
b11111111111111111111111111111110 u
b11 c
b11 y
b11 <"
b11 7
b11 @
b11 [
b11 ^
b11 p
b1001 ]
b10 m
b10 }
b10 >"
b10 f
b10 2"
b10 8"
b111 g
b111 ."
b111 7"
b11000 T
b100 V
b100001110100000000000010 |
b100 9"
b100 0"
b10 /"
b111 +"
b11100001100001110100 8
b11100001100001110100000000000010 )
b11100001100001110100000000000010 2
b11100001100001110100000000000010 l
b11100001100001110100000000000010 D"
b10100 j
b10100 '"
b10100 )"
b11000 h
b11000 %"
b11000 6"
b10100 i
b10100 !"
b10100 #"
b10100 &"
b10000 (
b10000 0
b10000 k
b10000 ""
b10000 *"
b10000 C"
1$
#65
0$
#70
b100 d
b100 ("
b100 4"
b100 :"
b111 s
b111 b
b111 w
b111 ?"
b100 #
b100 *
b100 5
b100 n
b100 z
b100 3"
b100 @"
b111 !
b111 &
b111 +
b111 a
b111 ;"
b111 ="
b111 B"
b10011 u
b1100 c
b1100 y
b1100 <"
b10 7
b10 @
b10 [
b10 ^
b10 p
b100 m
b100 }
b100 >"
b100 f
b100 2"
b100 8"
b11 g
b11 ."
b11 7"
b0 T
b101 V
b110101000000000100 |
b101 9"
b101 0"
b100 /"
b11 +"
b11100000000000110101 8
b11100000000000110101000000000100 )
b11100000000000110101000000000100 2
b11100000000000110101000000000100 l
b11100000000000110101000000000100 D"
b11000 j
b11000 '"
b11000 )"
b11100 h
b11100 %"
b11100 6"
b11000 i
b11000 !"
b11000 #"
b11000 &"
b10100 (
b10100 0
b10100 k
b10100 ""
b10100 *"
b10100 C"
1$
#75
0$
#80
b1011 d
b1011 ("
b1011 4"
b1011 :"
b1011 #
b1011 *
b1011 5
b1011 n
b1011 z
b1011 3"
b1011 @"
b1011 u
b100 c
b100 y
b100 <"
b0 7
b0 @
b0 [
b0 ^
b0 p
b101 g
b101 ."
b101 7"
b1000 T
b100001010101000000000100 |
b101 +"
b11100000100001010101 8
b11100000100001010101000000000100 )
b11100000100001010101000000000100 2
b11100000100001010101000000000100 l
b11100000100001010101000000000100 D"
b11100 j
b11100 '"
b11100 )"
b100000 h
b100000 %"
b100000 6"
b11100 i
b11100 !"
b11100 #"
b11100 &"
b11000 (
b11000 0
b11000 k
b11000 ""
b11000 *"
b11000 C"
1$
#85
0$
#90
b10 N
b10 6
b10 ?
b10 F
b10 o
b10 x
1q
1R
1O
b11111111111111111111111111111100 s
b11 b
b11 w
b11 ?"
b11 B
b11 !
b11 &
b11 +
b11 a
b11 ;"
b11 ="
b11 B"
b11 >
b11 D
b11 \
b1 7
b1 @
b1 [
b1 ^
b1 p
b111 m
b111 }
b111 >"
b111 f
b111 2"
b111 8"
b101 T
b1000 V
b1000 d
b1000 ("
b1000 4"
b1000 :"
b10101011000000000000111 |
b1000 9"
b1000 0"
b111 /"
b11100000010101011000 8
b1000 #
b1000 *
b1000 5
b1000 n
b1000 z
b1000 3"
b1000 @"
b11100000010101011000000000000111 )
b11100000010101011000000000000111 2
b11100000010101011000000000000111 l
b11100000010101011000000000000111 D"
b100000 j
b100000 '"
b100000 )"
b100000000000000000000000000001000 u
b1011 c
b1011 y
b1011 <"
b100100 h
b100100 %"
b100100 6"
b100000 i
b100000 !"
b100000 #"
b100000 &"
b11100 (
b11100 0
b11100 k
b11100 ""
b11100 *"
b11100 C"
1$
#95
0$
#100
b0 N
0q
b0 Q
b1011000 d
b1011000 ("
b1011000 4"
b1011000 :"
b110000 s
1-"
1;
0R
0O
b110000 b
b110000 w
b110000 ?"
b0 6
b0 ?
b0 F
b0 o
b0 x
0t
b1011000 #
b1011000 *
b1011000 5
b1011000 n
b1011000 z
b1011000 3"
b1011000 @"
b1 -
b1 :
b1 W
b1 `
b10 3
b10 =
b10 X
b10 _
b10 {
14
09
1Y
0Z
b0 B
0,
bx !
bx &
bx +
bx a
bx ;"
bx ="
bx B"
b1011000 u
b101000 c
b101000 y
b101000 <"
b0 >
b0 D
b0 \
b0 7
b0 @
b0 [
b0 ^
b0 p
b110100010 ]
0E
b110000 m
b110000 }
b110000 >"
b1100 f
b1100 2"
b1100 8"
b1111 g
b1111 ."
b1111 7"
b10 U
b100000 T
b0 V
b0 A
b0 G
b1100 |
b0 9"
b0 0"
b1100 /"
b0 +"
b1010000000000000 8
1M
b1010000000000000000000001100 )
b1010000000000000000000001100 2
b1010000000000000000000001100 l
b1010000000000000000000001100 D"
b100100 j
b100100 '"
b100100 )"
b10 C
b10 H
b10 P
b101000 h
b101000 %"
b101000 6"
b100100 i
b100100 !"
b100100 #"
b100100 &"
b100000 (
b100000 0
b100000 k
b100000 ""
b100000 *"
b100000 C"
1$
#105
0$
